winhye_common/__init__.py
winhye_common/config/__init__.py
winhye_common/config/apollo_client.py
winhye_common/config/config.yaml
winhye_common/config/config_client.py
winhye_common/config/config_group.py
winhye_common/config/configger.py
winhye_common/mqtt/__init__.py
winhye_common/mqtt/mqtt_base.py
winhye_common/session/__init__.py
winhye_common/session/database.py
winhye_common/session/db.py
winhye_common/session/session_redis.py
winhye_common/utils/__init__.py
winhye_common/utils/cookie_ras.py
winhye_common/utils/exception_base.py
winhye_common/utils/oss_base.py
winhye_common/utils/oss_temporary_permissions.py
winhye_common/utils/sms.py
winhye_common/winhye_handlers/__init__.py
winhye_common/winhye_handlers/file_handler.py
winhye_common/winhye_handlers/time_handler.py
winhye_common/winhye_logger/__init__.py
winhye_common/winhye_logger/ding_alarm.py
winhye_common/winhye_logger/filter.py
winhye_common/winhye_logger/weather.py
winhye_common-0.4.6.dist-info/LICENSE
winhye_common-0.4.6.dist-info/METADATA
winhye_common-0.4.6.dist-info/WHEEL
winhye_common-0.4.6.dist-info/top_level.txt
winhye_common-0.4.6.dist-info/RECORD
