Metadata-Version: 2.1
Name: winhye-common
Version: 0.4.6
Summary: public package including ES, logging, oss, db...
Home-page: https://e.gitee.com/winhye998/repos/winhye998/winhye-common
Author: 千城
Author-email: qiancheng0402@163.com
License: UNKNOWN
Platform: UNKNOWN
Classifier: Programming Language :: Python :: 3.6
Classifier: Programming Language :: Python :: 3.7
Classifier: Programming Language :: Python :: 3.8
Classifier: Programming Language :: Python :: 3.9
Classifier: License :: OSI Approved :: GNU Affero General Public License v3 or later (AGPLv3+)
Classifier: Operating System :: OS Independent
Requires-Python: >=3.6
License-File: LICENSE
Requires-Dist: flask
Requires-Dist: requests
Requires-Dist: paho-mqtt
Requires-Dist: websocket-server
Requires-Dist: sqlalchemy
Requires-Dist: psycopg2
Requires-Dist: oss2
Requires-Dist: crypto
Requires-Dist: gevent
Requires-Dist: alibabacloud-dysmsapi20170525
Requires-Dist: alibabacloud-sts20150401
Requires-Dist: redis
